aliyunsdkqianzhou/__init__.py
aliyunsdkqianzhou/request/__init__.py
aliyunsdkqianzhou/request/v20211111/AICreateSessionMessageRequest.py
aliyunsdkqianzhou/request/v20211111/CreateDiagnosisRequest.py
aliyunsdkqianzhou/request/v20211111/GetClusterRequest.py
aliyunsdkqianzhou/request/v20211111/GetClusterWarningRequest.py
aliyunsdkqianzhou/request/v20211111/GetDiagnosisResultRequest.py
aliyunsdkqianzhou/request/v20211111/GetUserClusterWarningRequest.py
aliyunsdkqianzhou/request/v20211111/GetWebshellTokenRequest.py
aliyunsdkqianzhou/request/v20211111/HelloRequest.py
aliyunsdkqianzhou/request/v20211111/ListClusterDeprecatedAPIRequest.py
aliyunsdkqianzhou/request/v20211111/ListClusterImagesRequest.py
aliyunsdkqianzhou/request/v20211111/ListUserClustersRequest.py
aliyunsdkqianzhou/request/v20211111/QueryByInstanceInfoRequest.py
aliyunsdkqianzhou/request/v20211111/QueryNodeInfoRequest.py
aliyunsdkqianzhou/request/v20211111/__init__.py
aliyun_python_sdk_qianzhou-1.0.0.dist-info/LICENSE
aliyun_python_sdk_qianzhou-1.0.0.dist-info/METADATA
aliyun_python_sdk_qianzhou-1.0.0.dist-info/WHEEL
aliyun_python_sdk_qianzhou-1.0.0.dist-info/top_level.txt
aliyun_python_sdk_qianzhou-1.0.0.dist-info/RECORD
